dietkit/__init__.py
dietkit/elements.py
dietkit/evaluator.py
dietkit/loader.py
dietkit/visualizer.py
dietkit/samples/korean_standard_criteria.csv
dietkit/samples/sample_diet_expert_eng.csv
dietkit/samples/sample_diet_expert_kor.csv
dietkit/samples/sample_diet_ml_eng.csv
dietkit/samples/sample_diet_ml_kor.csv
dietkit/samples/sample_diet_or_eng.csv
dietkit/samples/sample_diet_or_kor.csv
dietkit/samples/sample_ingredients_eng.csv
dietkit/samples/sample_ingredients_kor.csv
dietkit/samples/sample_menus_eng.csv
dietkit/samples/sample_menus_kor.csv
dietkit-0.0.11.dist-info/LICENSE
dietkit-0.0.11.dist-info/METADATA
dietkit-0.0.11.dist-info/WHEEL
dietkit-0.0.11.dist-info/top_level.txt
dietkit-0.0.11.dist-info/RECORD
