Metadata-Version: 2.1
Name: dietkit
Version: 0.0.11
Summary: Tools for management diet and its components
Home-page: https://github.com/pki663/dietkit
Author: Soohyeok Kim
Author-email: sooo@unist.ac.kr
License: UNKNOWN
Project-URL: Bug Tracker, https://github.com/pki663/dietkit/issues
Platform: UNKNOWN
Classifier: Programming Language :: Python :: 3.7
Classifier: Natural Language :: Korean
Classifier: Natural Language :: English
Classifier: Operating System :: OS Independent
Classifier: License :: OSI Approved :: GNU Lesser General Public License v2 or later (LGPLv2+)
Requires-Python: >=3.7
License-File: LICENSE
